n8n_manager/__init__.py
n8n_manager/api/__init__.py
n8n_manager/api/credentials.py
n8n_manager/api/executions.py
n8n_manager/api/workflows.py
n8n_manager/cli/__init__.py
n8n_manager/cli/main.py
n8n_manager/client.py
n8n_manager/exceptions.py
n8n_manager/models/__init__.py
n8n_manager/models/credential.py
n8n_manager/models/execution.py
n8n_manager/models/workflow.py
n8n_manager/utils/__init__.py
n8n_manager/utils/templating.py
n8n_flow_manager-0.1.3.dist-info/METADATA
n8n_flow_manager-0.1.3.dist-info/WHEEL
n8n_flow_manager-0.1.3.dist-info/entry_points.txt
n8n_flow_manager-0.1.3.dist-info/licenses/LICENSE
n8n_flow_manager-0.1.3.dist-info/RECORD
