Metadata-Version: 2.4
Name: n8n-flow-manager
Version: 0.1.3
Summary: A robust SDK and CLI for n8n workflow automation with DevOps capabilities
License: MIT
License-File: LICENSE
Keywords: n8n,automation,workflow,devops,cli,async,api
Author: Mariano Gobea
Author-email: gobeamariano@gmail.com
Requires-Python: >=3.9,<4.0
Classifier: Development Status :: 4 - Beta
Classifier: Framework :: AsyncIO
Classifier: Intended Audience :: Developers
Classifier: License :: OSI Approved :: MIT License
Classifier: Programming Language :: Python :: 3
Classifier: Programming Language :: Python :: 3.9
Classifier: Programming Language :: Python :: 3.10
Classifier: Programming Language :: Python :: 3.11
Classifier: Programming Language :: Python :: 3.12
Classifier: Programming Language :: Python :: 3.13
Classifier: Programming Language :: Python :: 3.14
Classifier: Topic :: Software Development :: Libraries :: Python Modules
Classifier: Topic :: System :: Systems Administration
Requires-Dist: click (>=8.0.0,<8.2.0)
Requires-Dist: httpx (>=0.27.0,<0.28.0)
Requires-Dist: jinja2 (>=3.1.0,<4.0.0)
Requires-Dist: pydantic (>=2.5.0,<3.0.0)
Requires-Dist: python-dotenv (>=1.0.0,<2.0.0)
Requires-Dist: rich (>=13.7.0,<14.0.0)
Requires-Dist: typer[all] (>=0.12.0,<0.13.0)
Project-URL: Documentation, https://github.com/Mgobeaalcoba/n8n-flow-manager#readme
Project-URL: Homepage, https://github.com/Mgobeaalcoba/n8n-flow-manager
Project-URL: Repository, https://github.com/Mgobeaalcoba/n8n-flow-manager
